{
  "sprites" : [
    {
      "name" : "idle",
      "filename" : "skeleton-idle.png",
      "location" : [0, 0],
      "size" : [64, 64],
      "scale" : 4,
      "number_of_frames" : 4,
      "dt_per_frame" : 0.1
    },
    {
      "name" : "running",
      "filename" : "skeleton-running.png",
      "location" : [0, 0],
      "size" : [64, 64],
      "scale" : 4,
      "number_of_frames" : 12,
      "dt_per_frame" : 0.1
    },
    {
      "name" : "attacking",
      "filename" : "skeleton-attack.png",
      "location" : [0, 0],
      "size" : [64, 64],
      "scale" : 4,
      "number_of_frames" : 13,
      "dt_per_frame" : 0.1
    },
    {
      "name" : "dying",
      "filename" : "skeleton-death.png",
      "location" : [0, 0],
      "size" : [64, 64],
      "scale" : 4,
      "number_of_frames" : 13,
      "dt_per_frame" : 0.1
    }
  ],
  "physics" : {
    "velocity": [0, 0],
    "acceleration" : [0, -30],
    "gravity": -30.0,
    "damping": 0.9,
    "walk_acceleration": 20.0,
    "jump_velocity": 20.0,
    "terminal_velocity": 30.0
  },
  "size": [1,2],
  "health" : 15,
  "max_health" : 15,
  "damage" : 4,
  "detection_distance" : [5,2],
  "invulnerable" : false,
  "attack_range" : 0
}